setup.py
rf_probability/Binomialdistribution.py
rf_probability/Gaussiandistribution.py
rf_probability/Generaldistribution.py
rf_probability/__init__.py
rf_probability.egg-info/PKG-INFO
rf_probability.egg-info/SOURCES.txt
rf_probability.egg-info/dependency_links.txt
rf_probability.egg-info/not-zip-safe
rf_probability.egg-info/top_level.txt