Metadata-Version: 1.0
Name: rf-probability
Version: 0.1
Summary: Gaussian and Binomial distributions
Home-page: UNKNOWN
Author: Ryan Fox
Author-email: ryanfox212@gmail.com
License: UNKNOWN
Platform: UNKNOWN
